{
	"images": [
		{
			"file_name": "K-008120_0_0_0_0_60_000_200.png",
			"width": 976,
			"height": 1280,
			"imgfile": "K-008120_0_0_0_0_60_000_200.png",
			"drug_N": "K-008120",
			"drug_S": "정상알약",
			"back_color": "검은색 배경",
			"drug_dir": "앞면",
			"light_color": "전구색",
			"camera_la": 60,
			"camera_lo": 0,
			"size": 200,
			"item_seq": "199902459",
			"leng_long": "12.5",
			"leng_short": "6.6",
			"thick": "4.2",
			"id": 1,
			"dl_idx": "8119",
			"dl_mapping_code": "K-008120",
			"dl_name": "진코바정 80mg",
			"dl_name_en": "Ginkoba Tab. 80mg",
			"img_key": "http://connectdi.com/design/img/drug/147427677718300062.jpg",
			"dl_material": "은행엽건조엑스",
			"dl_material_en": "Ginkgo Leaf Ext.",
			"dl_custom_shape": "정제, 저작정",
			"dl_company": "알보젠코리아(주)",
			"dl_company_en": "Alvogen Korea",
			"di_company_mf": "(주)한국파마",
			"di_company_mf_en": "Korea Pharma",
			"di_item_permit_date": "19990104",
			"di_class_no": "[02190]기타의 순환계용약",
			"di_etc_otc_code": "일반의약품",
			"di_edi_code": "652603670,655904030",
			"chart": "녹색의 장방형 필름코팅정제 ",
			"drug_shape": "장방형",
			"print_front": "DP",
			"print_back": "J분할선80",
			"color_class1": "연두",
			"color_class2": "",
			"line_front": "",
			"line_back": "-",
			"img_regist_ts": "20141030",
			"form_code_name": "필름코팅정",
			"mark_code_front_anal": "",
			"mark_code_back_anal": "",
			"mark_code_front_img": "",
			"mark_code_back_img": "",
			"mark_code_front": "",
			"mark_code_back": "",
			"change_date": "20200723"
		}
	],
	"type": "instances",
	"annotations": [
		{
			"area": 71224,
			"iscrowd": 0,
			"bbox": [
				342,
				466,
				307,
				232
			],
			"category_id": 1,
			"ignore": 0,
			"segmentation": [],
			"id": 1,
			"image_id": 1
		}
	],
	"categories": [
		{
			"supercategory": "pill",
			"id": 1,
			"name": "Drug"
		}
	]
}